pywhoami/__init__.py
pywhoami/__main__.py
pywhoami/asgi.py
pywhoami-1.1.1.dist-info/LICENSE
pywhoami-1.1.1.dist-info/METADATA
pywhoami-1.1.1.dist-info/WHEEL
pywhoami-1.1.1.dist-info/top_level.txt
pywhoami-1.1.1.dist-info/RECORD
