Metadata-Version: 2.1
Name: pywhoami
Version: 1.1.1
Summary: A Simple HTTP Request Analysis Server
Home-page: https://github.com/sirfuzzalot/pywhoami
Author: Tom Saunders
License: MIT
Project-URL: Tracker, https://github.com/sirfuzzalot/pywhoami/issues
Project-URL: Documentation, https://github.com/sirfuzzalot/pywhoami
Project-URL: Source, https://github.com/sirfuzzalot/pywhoami
Classifier: Development Status :: 4 - Beta
Classifier: Framework :: AsyncIO
Classifier: Intended Audience :: Developers
Classifier: Intended Audience :: System Administrators
Classifier: License :: OSI Approved :: MIT License
Classifier: Programming Language :: Python
Classifier: Programming Language :: Python :: 3
Classifier: Programming Language :: Python :: 3 :: Only
Classifier: Programming Language :: Python :: 3.8
Classifier: Programming Language :: Python :: 3.9
Classifier: Programming Language :: Python :: 3.10
Classifier: Operating System :: OS Independent
Classifier: Topic :: Internet :: WWW/HTTP :: HTTP Servers
Classifier: Topic :: Software Development
Classifier: Topic :: Utilities
Requires-Python: >=3.8
License-File: LICENSE
Requires-Dist: Hypercorn (==0.13.2)
Requires-Dist: Quart (==0.17.0)
